django_securebox/__init__.py
django_securebox/apps.py
django_securebox/middleware.py
django_securebox/models.py
django_securebox/signals.py
django_securebox/utils.py
django_securebox/migrations/0001_initial.py
django_securebox/migrations/__init__.py
django_securebox-0.1.5.dist-info/LICENSE
django_securebox-0.1.5.dist-info/METADATA
django_securebox-0.1.5.dist-info/WHEEL
django_securebox-0.1.5.dist-info/top_level.txt
django_securebox-0.1.5.dist-info/RECORD
