Metadata-Version: 2.1
Name: django-securebox
Version: 0.1.5
Summary: Djange SecureBox implementation -- encrypts data for a Django User, but allows for transparent access within a Session
Home-page: https://github.com/henryk/django-securebox
Author: Henryk Plötz
Author-email: henryk@ploetzli.ch
License: GNU General Public License v3
Keywords: django_securebox
Platform: UNKNOWN
Classifier: Development Status :: 2 - Pre-Alpha
Classifier: Intended Audience :: Developers
Classifier: License :: OSI Approved :: GNU Lesser General Public License v3 or later (LGPLv3+)
Classifier: Natural Language :: English
Classifier: Programming Language :: Python :: 3
Classifier: Programming Language :: Python :: 3.4
Classifier: Programming Language :: Python :: 3.5
Classifier: Programming Language :: Python :: 3.6
Requires-Dist: django (>=1.11)
Requires-Dist: pynacl (==1.4.*)
